Metadata-Version: 2.1
Name: squares
Version: 0.0.0
Summary: An identicon generator
Home-page: https://github.com/aaeg/squares
Author: Alee
Author-email: mazaeela@gmail.com
License: MIT
Keywords: identicon,pil
Platform: UNKNOWN
Classifier: Programming Language :: Python :: 3
Classifier: License :: OSI Approved :: MIT License
License-File: LICENSE
